[
  {
    "Ticker": "UNH",
    "Period": "Q4",
    "Year": 2021,
    "Interval": "quarterly",
    "Metric": "Revenue",
    "ParentMetric": "Revenue",
    "Value": 73743000000,
    "Section": "Financials",
    "SourcedFrom": "EarningsSupplement",
    "PeriodEndDate": "2021-12-31",
    "Unit": "Dollars"
  },
  {
    "Ticker": "UNH",
    "Period": "Q4",
    "Year": 2021,
    "Interval": "quarterly",
    "Metric": "Medical",
    "ParentMetric": "OperatingExpenses",
    "Value": 48159000000,
    "Section": "Financials",
    "SourcedFrom": "EarningsSupplement",
    "PeriodEndDate": "2021-12-31",
    "Unit": "Dollars"
  },
  {
    "Ticker": "UNH",
    "Period": "Q4",
    "Year": 2021,
    "Interval": "quarterly",
    "Metric": "Operating",
    "ParentMetric": "OperatingExpenses",
    "Value": 11272000000,
    "Section": "Financials",
    "SourcedFrom": "EarningsSupplement",
    "PeriodEndDate": "2021-12-31",
    "Unit": "Dollars"
  },
  {
    "Ticker": "UNH",
    "Period": "Q4",
    "Year": 2021,
    "Interval": "quarterly",
    "Metric": "CostOfProducts",
    "ParentMetric": "OperatingExpenses",
    "Value": 8000000000,
    "Section": "Financials",
    "SourcedFrom": "EarningsSupplement",
    "PeriodEndDate": "2021-12-31",
    "Unit": "Dollars"
  },
  {
    "Ticker": "UNH",
    "Period": "Q4",
    "Year": 2021,
    "Interval": "quarterly",
    "Metric": "DepreciationAndAmortization",
    "ParentMetric": "OperatingExpenses",
    "Value": 771000000,
    "Section": "Financials",
    "SourcedFrom": "EarningsSupplement",
    "PeriodEndDate": "2021-12-31",
    "Unit": "Dollars"
  },
  {
    "Ticker": "UNH",
    "Period": "Q4",
    "Year": 2021,
    "Interval": "quarterly",
    "Metric": "OperatingIncome",
    "ParentMetric": "OperatingIncome",
    "Value": 5541000000,
    "Section": "Financials",
    "SourcedFrom": "EarningsSupplement",
    "PeriodEndDate": "2021-12-31",
    "Unit": "Dollars"
  },
  {
    "Ticker": "UNH",
    "Period": "Q4",
    "Year": 2021,
    "Interval": "quarterly",
    "Metric": "NetIncome",
    "ParentMetric": "NetIncome",
    "Value": 4071000000,
    "Section": "Financials",
    "SourcedFrom": "EarningsSupplement",
    "PeriodEndDate": "2021-12-31",
    "Unit": "Dollars"
  },
  {
    "Ticker": "UNH",
    "Period": "Q4",
    "Year": 2021,
    "Interval": "quarterly",
    "Metric": "Diluted",
    "ParentMetric": "EPS",
    "Value": 4.26,
    "Section": "Financials",
    "SourcedFrom": "EarningsSupplement",
    "PeriodEndDate": "2021-12-31",
    "Unit": "Dollars"
  },
  {
    "Ticker": "UNH",
    "Period": "Q4",
    "Year": 2021,
    "Interval": "quarterly",
    "Metric": "TotalAssets",
    "ParentMetric": "TotalAssets",
    "Value": 212206000000,
    "Section": "Financials",
    "SourcedFrom": "EarningsSupplement",
    "PeriodEndDate": "2021-12-31",
    "Unit": "Dollars"
  },
  {
    "Ticker": "UNH",
    "Period": "Q4",
    "Year": 2021,
    "Interval": "quarterly",
    "Metric": "TotalStockholdersEquity",
    "ParentMetric": "TotalStockholdersEquity",
    "Value": 75045000000,
    "Section": "Financials",
    "SourcedFrom": "EarningsSupplement",
    "PeriodEndDate": "2021-12-31",
    "Unit": "Dollars"
  },
  {
    "Ticker": "UNH",
    "Period": "Q4",
    "Year": 2021,
    "Interval": "quarterly",
    "Metric": "CashAndCashEquivalents",
    "ParentMetric": "CashAndDebt",
    "Value": 21375000000,
    "Section": "Financials",
    "SourcedFrom": "EarningsSupplement",
    "PeriodEndDate": "2021-12-31",
    "Unit": "Dollars"
  },
  {
    "Ticker": "UNH",
    "Period": "Q4",
    "Year": 2021,
    "Interval": "quarterly",
    "Metric": "Debt",
    "ParentMetric": "CashAndDebt",
    "Value": 46003000000,
    "Section": "Financials",
    "SourcedFrom": "EarningsSupplement",
    "PeriodEndDate": "2021-12-31",
    "Unit": "Dollars"
  },
  {
    "Ticker": "UNH",
    "Period": "Q4",
    "Year": 2021,
    "Interval": "quarterly",
    "Metric": "Premiums",
    "ParentMetric": "RevenueBySegment",
    "Value": 57547000000,
    "Section": "KPI",
    "SourcedFrom": "EarningsSupplement",
    "PeriodEndDate": "2021-12-31",
    "Unit": "Dollars"
  },
  {
    "Ticker": "UNH",
    "Period": "Q4",
    "Year": 2021,
    "Interval": "quarterly",
    "Metric": "Products",
    "ParentMetric": "RevenueBySegment",
    "Value": 8961000000,
    "Section": "KPI",
    "SourcedFrom": "EarningsSupplement",
    "PeriodEndDate": "2021-12-31",
    "Unit": "Dollars"
  },
  {
    "Ticker": "UNH",
    "Period": "Q4",
    "Year": 2021,
    "Interval": "quarterly",
    "Metric": "Services",
    "ParentMetric": "RevenueBySegment",
    "Value": 6422000000,
    "Section": "KPI",
    "SourcedFrom": "EarningsSupplement",
    "PeriodEndDate": "2021-12-31",
    "Unit": "Dollars"
  },
  {
    "Ticker": "UNH",
    "Period": "Q4",
    "Year": 2021,
    "Interval": "quarterly",
    "Metric": "InvestmentAndOtherIncome",
    "ParentMetric": "RevenueBySegment",
    "Value": 813000000,
    "Section": "KPI",
    "SourcedFrom": "EarningsSupplement",
    "PeriodEndDate": "2021-12-31",
    "Unit": "Dollars"
  },
  {
    "Ticker": "UNH",
    "Period": "Q4",
    "Year": 2021,
    "Interval": "quarterly",
    "Metric": "EmployerAndIndividual",
    "ParentMetric": "UnitedHealthcareRevenue",
    "Value": 15355000000,
    "Section": "KPI",
    "SourcedFrom": "EarningsSupplement",
    "PeriodEndDate": "2021-12-31",
    "Unit": "Dollars"
  },
  {
    "Ticker": "UNH",
    "Period": "Q4",
    "Year": 2021,
    "Interval": "quarterly",
    "Metric": "MedicareAndRetirement",
    "ParentMetric": "UnitedHealthcareRevenue",
    "Value": 24843000000,
    "Section": "KPI",
    "SourcedFrom": "EarningsSupplement",
    "PeriodEndDate": "2021-12-31",
    "Unit": "Dollars"
  },
  {
    "Ticker": "UNH",
    "Period": "Q4",
    "Year": 2021,
    "Interval": "quarterly",
    "Metric": "CommunityAndState",
    "ParentMetric": "UnitedHealthcareRevenue",
    "Value": 14133000000,
    "Section": "KPI",
    "SourcedFrom": "EarningsSupplement",
    "PeriodEndDate": "2021-12-31",
    "Unit": "Dollars"
  },
  {
    "Ticker": "UNH",
    "Period": "Q4",
    "Year": 2021,
    "Interval": "quarterly",
    "Metric": "OptumHealth",
    "ParentMetric": "OptumRevenue",
    "Value": 14550000000,
    "Section": "KPI",
    "SourcedFrom": "EarningsSupplement",
    "PeriodEndDate": "2021-12-31",
    "Unit": "Dollars"
  },
  {
    "Ticker": "UNH",
    "Period": "Q4",
    "Year": 2021,
    "Interval": "quarterly",
    "Metric": "OptumInsight",
    "ParentMetric": "OptumRevenue",
    "Value": 3251000000,
    "Section": "KPI",
    "SourcedFrom": "EarningsSupplement",
    "PeriodEndDate": "2021-12-31",
    "Unit": "Dollars"
  },
  {
    "Ticker": "UNH",
    "Period": "Q4",
    "Year": 2021,
    "Interval": "quarterly",
    "Metric": "OptumRx",
    "ParentMetric": "OptumRevenue",
    "Value": 23849000000,
    "Section": "KPI",
    "SourcedFrom": "EarningsSupplement",
    "PeriodEndDate": "2021-12-31",
    "Unit": "Dollars"
  },
  {
    "Ticker": "UNH",
    "Period": "Q4",
    "Year": 2021,
    "Interval": "quarterly",
    "Metric": "RiskBased",
    "ParentMetric": "CommercialPeopleServed",
    "Value": 7985000,
    "Section": "KPI",
    "SourcedFrom": "EarningsSupplement",
    "PeriodEndDate": "2021-12-31",
    "Unit": "Count"
  },
  {
    "Ticker": "UNH",
    "Period": "Q4",
    "Year": 2021,
    "Interval": "quarterly",
    "Metric": "FeeBased",
    "ParentMetric": "CommercialPeopleServed",
    "Value": 18595000,
    "Section": "KPI",
    "SourcedFrom": "EarningsSupplement",
    "PeriodEndDate": "2021-12-31",
    "Unit": "Count"
  },
  {
    "Ticker": "UNH",
    "Period": "Q4",
    "Year": 2021,
    "Interval": "quarterly",
    "Metric": "MedicareAdvantage",
    "ParentMetric": "CommunityAndSeniorPeopleServed",
    "Value": 6490000,
    "Section": "KPI",
    "SourcedFrom": "EarningsSupplement",
    "PeriodEndDate": "2021-12-31",
    "Unit": "Count"
  },
  {
    "Ticker": "UNH",
    "Period": "Q4",
    "Year": 2021,
    "Interval": "quarterly",
    "Metric": "Medicaid",
    "ParentMetric": "CommunityAndSeniorPeopleServed",
    "Value": 7655000,
    "Section": "KPI",
    "SourcedFrom": "EarningsSupplement",
    "PeriodEndDate": "2021-12-31",
    "Unit": "Count"
  },
  {
    "Ticker": "UNH",
    "Period": "Q4",
    "Year": 2021,
    "Interval": "quarterly",
    "Metric": "MedicareSupplement",
    "ParentMetric": "CommunityAndSeniorPeopleServed",
    "Value": 4395000,
    "Section": "KPI",
    "SourcedFrom": "EarningsSupplement",
    "PeriodEndDate": "2021-12-31",
    "Unit": "Count"
  },
  {
    "Ticker": "UNH",
    "Period": "Q4",
    "Year": 2021,
    "Interval": "quarterly",
    "Metric": "TotalMedicalPeopleServed",
    "ParentMetric": "TotalMedicalPeopleServed",
    "Value": 50630000,
    "Section": "KPI",
    "SourcedFrom": "EarningsSupplement",
    "PeriodEndDate": "2021-12-31",
    "Unit": "Count"
  },
  {
    "Ticker": "UNH",
    "Period": "Q4",
    "Year": 2021,
    "Interval": "quarterly",
    "Metric": "OptumHealthConsumersServed",
    "ParentMetric": "OptumHealthConsumersServed",
    "Value": 100000000,
    "Section": "KPI",
    "SourcedFrom": "EarningsSupplement",
    "PeriodEndDate": "2021-12-31",
    "Unit": "Count"
  },
  {
    "Ticker": "UNH",
    "Period": "Q4",
    "Year": 2021,
    "Interval": "quarterly",
    "Metric": "OptumInsightContractBacklog",
    "ParentMetric": "OptumInsightContractBacklog",
    "Value": 22400000000,
    "Section": "KPI",
    "SourcedFrom": "EarningsSupplement",
    "PeriodEndDate": "2021-12-31",
    "Unit": "Dollars"
  },
  {
    "Ticker": "UNH",
    "Period": "Q4",
    "Year": 2021,
    "Interval": "quarterly",
    "Metric": "OptumRxQuarterlyAdjustedScripts",
    "ParentMetric": "OptumRxQuarterlyAdjustedScripts",
    "Value": 353000000,
    "Section": "KPI",
    "SourcedFrom": "EarningsSupplement",
    "PeriodEndDate": "2021-12-31",
    "Unit": "Count"
  },
  {
    "Ticker": "UNH",
    "Period": "Q4",
    "Year": 2021,
    "Interval": "quarterly",
    "Metric": "MedicalCareRatio",
    "ParentMetric": "MedicalCareRatio",
    "Value": 83.7,
    "Section": "KPI",
    "SourcedFrom": "EarningsSupplement",
    "PeriodEndDate": "2021-12-31",
    "Unit": "Percent"
  }
]